aws_cdk_modules/__init__.py
aws_cdk_modules/base.py
aws_cdk_modules/network/__init__.py
aws_cdk_modules/network/module.py
aws_cdk_modules-1.0.0.dev2.dist-info/METADATA
aws_cdk_modules-1.0.0.dev2.dist-info/WHEEL
aws_cdk_modules-1.0.0.dev2.dist-info/entry_points.txt
aws_cdk_modules-1.0.0.dev2.dist-info/licenses/LICENSE
aws_cdk_modules-1.0.0.dev2.dist-info/RECORD
