Metadata-Version: 2.4
Name: aws-cdk-modules
Version: 1.0.0.dev2
Summary: Python repository for AWS CDK modules
Project-URL: Documentation, https://collier-p-charlie.github.io/aws-cdk-modules
Project-URL: Repository, https://github.com/collier-p-charlie/aws-cdk-modules
Project-URL: Issues, https://github.com/collier-p-charlie/aws-cdk-modules/issues
Project-URL: Changelog, https://github.com/collier-p-charlie/aws-cdk-modules/blob/main/CHANGELOG.md
Author-email: Charlie Collier <collier.p.charlie@gmail.com>
Maintainer-email: Charlie Collier <collier.p.charlie@gmail.com>
License-Expression: MIT
License-File: LICENSE
Classifier: Framework :: Hatch
Classifier: Operating System :: OS Independent
Classifier: Programming Language :: Python :: 3
Requires-Python: >=3.12
Requires-Dist: aws-cdk-lib>=2.211.0
Requires-Dist: constructs>=10.4.2
Provides-Extra: docs
Requires-Dist: mkdocs; extra == 'docs'
Requires-Dist: mkdocs-material; extra == 'docs'
Requires-Dist: mkdocstrings[python]; extra == 'docs'
Provides-Extra: test
Requires-Dist: mypy; extra == 'test'
Requires-Dist: pre-commit; extra == 'test'
Requires-Dist: pytest; extra == 'test'
Requires-Dist: pytest-cov; extra == 'test'
Requires-Dist: ruff; extra == 'test'
